{
  "schemaVersion": 1,
  "users": [
    {
      "id": 1,
      "displayName": "Carleigh",
      "progress": {
        "hintsUsed": 0,
        "inventory": [],
        "storedHints": [],
        "strikes": 0,
        "currentScore": 0
      },
      "id": 2,
      "displayName": "Lukin",
      "progress": {
        "hintsUsed": 0,
        "inventory": [],
        "storedHints": [],
        "strikes": 0,
        "currentScore": 0
      },
      "id": 3,
      "displayName": "Bianca",
      "progress": {
        "hintsUsed": 0,
        "inventory": [],
        "storedHints": [],
        "strikes": 0,
        "currentScore": 0
      },
      "id": 4,
      "displayName": "Charlotte",
      "progress": {
        "hintsUsed": 0,
        "inventory": [],
        "storedHints": [],
        "strikes": 0,
        "currentScore": 0
      },

      
      "sessions": [
        {
          "gameID": null,
          "roomID": null,
          "difficulty": null,
          "puzzles": [],
          "completedCount": 0,
          "score": 0,
          "isPaused": false,
          "isOver": false,
          "startTime": null,
          "endTime": null,
          "facade": {
            "facadeID": null,
            "currentState": null,
            "lastAction": null,
            "sessionStartTime": null
          }
        }
      ]
    }
  ]
}

